obonet/__init__.py
obonet/io.py
obonet/py.typed
obonet/read.py
obonet-1.1.0.dist-info/LICENSE.md
obonet-1.1.0.dist-info/METADATA
obonet-1.1.0.dist-info/WHEEL
obonet-1.1.0.dist-info/top_level.txt
obonet-1.1.0.dist-info/RECORD
