Metadata-Version: 2.1
Name: obonet
Version: 1.1.0
Summary: Parse OBO formatted ontologies into networkx
Author-email: Daniel Himmelstein <daniel.himmelstein@gmail.com>
License: BSD-2-Clause-Patent
Project-URL: Homepage, https://github.com/dhimmel/obonet
Project-URL: Source, https://github.com/dhimmel/obonet
Project-URL: Tracker, https://github.com/dhimmel/obonet/issues
Keywords: obo,ontology,networkx,parser,network
Classifier: Intended Audience :: Science/Research
Classifier: License :: OSI Approved :: BSD License
Classifier: Operating System :: OS Independent
Classifier: Programming Language :: Python
Classifier: Programming Language :: Python :: 3
Classifier: Topic :: Scientific/Engineering :: Bio-Informatics
Classifier: Topic :: Scientific/Engineering :: Information Analysis
Requires-Python: >=3.8
License-File: LICENSE.md
Requires-Dist: networkx
Provides-Extra: dev
Requires-Dist: pre-commit ; extra == 'dev'
Requires-Dist: pytest ; extra == 'dev'
